vallaipallam/__init__.py
vallaipallam/data.py
vallaipallam/errors.py
vallaipallam/interpreter.py
vallaipallam/lexer.py
vallaipallam/network.py
vallaipallam/parser.py
vallaipallam/shell.py
vallaipallam/tokens.py
vallaipallam/agenticai/__init__.py
vallaipallam/agenticai/ai.py
vallaipallam/agenticai/logo.png
vallaipallam/agenticai/main.py
vallaipallam/agenticai/systemprompt.txt
vallaipallam/agenticai/functions/call_function.py
vallaipallam/agenticai/functions/execute_network_commands.py
vallaipallam/agenticai/functions/get_file_content.py
vallaipallam/agenticai/functions/get_files_info.py
vallaipallam/agenticai/functions/run_program_file.py
vallaipallam/agenticai/functions/writefile.py
vallaipallam/agenticai/functions/__pycache__/__init__.py
vallaipallam-1.0.5.dist-info/METADATA
vallaipallam-1.0.5.dist-info/WHEEL
vallaipallam-1.0.5.dist-info/entry_points.txt
vallaipallam-1.0.5.dist-info/top_level.txt
vallaipallam-1.0.5.dist-info/RECORD
