Metadata-Version: 2.4
Name: vallaipallam
Version: 1.0.5
Summary: A Regional-based programming language,interpreter and agentic ai
Home-page: https://github.com/NishanthRaj707
Author: J. Nishanth Raj
Author-email: jpnishanthraj@email.com
Classifier: Programming Language :: Python :: 3
Classifier: License :: OSI Approved :: GNU General Public License v3 (GPLv3)
Classifier: Operating System :: OS Independent
Classifier: Natural Language :: Tamil
Requires-Python: >=3.7
Requires-Dist: psutil
Requires-Dist: google-genai
Dynamic: author
Dynamic: author-email
Dynamic: classifier
Dynamic: description
Dynamic: description-content-type
Dynamic: home-page
Dynamic: requires-dist
Dynamic: requires-python
Dynamic: summary
